exvis/__about__.py
exvis/__init__.py
exvis/visualize.py
exvis-0.1.0.dist-info/METADATA
exvis-0.1.0.dist-info/WHEEL
exvis-0.1.0.dist-info/entry_points.txt
exvis-0.1.0.dist-info/licenses/LICENSE
exvis-0.1.0.dist-info/RECORD
