Metadata-Version: 2.1
Name: exvis
Version: 0.1.0
Summary: exvis visualizes MIP instances based on their expressions (variables and constraints) as a graph.
Project-URL: Homepage, https://github.com/merschformann/exvis
Project-URL: Repository, https://github.com/merschformann/exvis
Author-email: Marius Merschformann <marius.merschformann@gmail.com>
Maintainer-email: Marius Merschformann <marius.merschformann@gmail.com>
License: MIT License
License-File: LICENSE
Keywords: mip,mixed-integer programming,operations research,optimization,visualization
Classifier: License :: OSI Approved :: MIT License
Classifier: Operating System :: OS Independent
Classifier: Programming Language :: Python :: 3
Classifier: Topic :: Scientific/Engineering :: Visualization
Requires-Python: >=3.10
Requires-Dist: matplotlib>=3.8.2
Requires-Dist: networkx>=3.2.1
